odoo8_addon_crm_autoalias-8.0.1.0.0-py2.7-nspkg.pth
odoo8_addon_crm_autoalias-8.0.1.0.0.dist-info/top_level.txt
odoo8_addon_crm_autoalias-8.0.1.0.0.dist-info/WHEEL
odoo8_addon_crm_autoalias-8.0.1.0.0.dist-info/RECORD
odoo8_addon_crm_autoalias-8.0.1.0.0.dist-info/metadata.json
odoo8_addon_crm_autoalias-8.0.1.0.0.dist-info/DESCRIPTION.rst
odoo8_addon_crm_autoalias-8.0.1.0.0.dist-info/METADATA
odoo8_addon_crm_autoalias-8.0.1.0.0.dist-info/namespace_packages.txt
odoo_addons/crm_autoalias/__openerp__.py
odoo_addons/crm_autoalias/hooks.py
odoo_addons/crm_autoalias/__init__.py
odoo_addons/crm_autoalias/README.rst
odoo_addons/crm_autoalias/view/crm_lead_view.xml
odoo_addons/crm_autoalias/model/__init__.py
odoo_addons/crm_autoalias/model/crm_lead.py
odoo_addons/crm_autoalias/test/test_autoalias.yml
